suffix_tree_tool/__init__.py
suffix_tree_tool/builder.py
suffix_tree_tool/cli.py
suffix_tree_tool-0.1.2.dist-info/METADATA
suffix_tree_tool-0.1.2.dist-info/WHEEL
suffix_tree_tool-0.1.2.dist-info/entry_points.txt
suffix_tree_tool-0.1.2.dist-info/licenses/LICENSE
suffix_tree_tool-0.1.2.dist-info/RECORD
