Metadata-Version: 2.4
Name: suffix-tree-tool
Version: 0.1.2
Summary: Generalized suffix tree generator and renderer
Project-URL: Homepage, https://github.com/EmericLaberge/suffix-tree-tool
Author-email: Emeric <emeric.laberge@umontreal.ca>
License: MIT License
License-File: LICENSE
Classifier: Intended Audience :: Science/Research
Classifier: License :: OSI Approved :: MIT License
Classifier: Programming Language :: Python :: 3
Classifier: Topic :: Scientific/Engineering :: Information Analysis
Requires-Python: >=3.9
Requires-Dist: networkx>=3.0
Requires-Dist: pydot>=1.4.2
